CGPCLI/Commands.py
CGPCLI/Connection.py
CGPCLI/Errors.py
CGPCLI/Parser.py
CGPCLI/__init__.py
CGPCLI-0.1.3.dist-info/LICENSE
CGPCLI-0.1.3.dist-info/METADATA
CGPCLI-0.1.3.dist-info/WHEEL
CGPCLI-0.1.3.dist-info/top_level.txt
CGPCLI-0.1.3.dist-info/RECORD
