Metadata-Version: 2.1
Name: CGPCLI
Version: 0.1.3
Summary: Package for CGP CLI access
Home-page: UNKNOWN
Author: Lesnikov Nikita
Author-email: nlesnikov@communigate.ru
License: UNKNOWN
Platform: UNKNOWN
Classifier: Programming Language :: Python :: 3
Classifier: License :: OSI Approved :: MIT License
Classifier: Operating System :: OS Independent
Requires-Python: >=3.6
